deepview_mcp/.env.example
deepview_mcp/__init__.py
deepview_mcp/cli.py
deepview_mcp/server.py
deepview_mcp/test.py
deepview_mcp-0.2.4.dist-info/LICENSE
deepview_mcp-0.2.4.dist-info/METADATA
deepview_mcp-0.2.4.dist-info/WHEEL
deepview_mcp-0.2.4.dist-info/entry_points.txt
deepview_mcp-0.2.4.dist-info/RECORD
