Metadata-Version: 2.3
Name: deepview-mcp
Version: 0.2.4
Summary: A Model Context Protocol server for analyzing large codebases using Gemini 2.0
License: MIT
Keywords: mcp,gemini,code-analysis,ai,ide
Author: Dmitry Degtyarev
Author-email: ddegtyarev@gmail.com
Requires-Python: >=3.10,<4.0
Classifier: Development Status :: 4 - Beta
Classifier: Intended Audience :: Developers
Classifier: License :: OSI Approved :: MIT License
Classifier: Programming Language :: Python :: 3
Classifier: Programming Language :: Python :: 3.10
Classifier: Programming Language :: Python :: 3.11
Classifier: Programming Language :: Python :: 3.12
Classifier: Programming Language :: Python :: 3.13
Classifier: Programming Language :: Python :: 3.8
Classifier: Programming Language :: Python :: 3.9
Classifier: Topic :: Software Development :: Libraries :: Python Modules
Requires-Dist: google-generativeai
Requires-Dist: mcp
Requires-Dist: pydantic
Requires-Dist: python-dotenv
Project-URL: Repository, https://github.com/ddegtyarev/deepview-mcp
